AUTHORS
LICENSE
MANIFEST.in
README.rst
setup.py
banner/__init__.py
banner/admin.py
banner/generator.py
banner/models.py
banner/tests.py
banner/fixtures/photosizes.json
banner/templates/banner/inclusion_tags/banner_block_gizmo.html
banner/templates/banner/inclusion_tags/banner_wide_gizmo.html
banner/templates/banner/inclusion_tags/codebanner_block.html
banner/templates/banner/inclusion_tags/codebanner_wide.html
banner/templates/banner/inclusion_tags/imagebanner_block.html
banner/templates/banner/inclusion_tags/imagebanner_wide.html
banner/templatetags/.banner_inclusion_tags.py.swp
banner/templatetags/__init__.py
banner/templatetags/banner_inclusion_tags.py
panya_banner.egg-info/PKG-INFO
panya_banner.egg-info/SOURCES.txt
panya_banner.egg-info/dependency_links.txt
panya_banner.egg-info/not-zip-safe
panya_banner.egg-info/requires.txt
panya_banner.egg-info/top_level.txt